{"settingEntity":{"featureNames":[],"styleTransferAlgorithmType":"image","seedType":"default","soundAlgorithmType":"transferLearning","soundOverlapFactor":0.5,"harVideoAugmentations":0,"taskType":"audioClassifier","soundIsCustomOverlapFactor":false,"handActionClassifierAugmentations":[],"iterationCount":25,"soundFeatureExtractionType":"audioFeaturePrint","handPoseClassifierAugmentations":[],"algorithmType":"maxEnt","soundClassifierMLPLayers":[2],"augmentations":[],"soundClassifierType":"logisticRegressor","soundTimeWindow":0.975,"transferLearningEmbeddingType":"dynamic"},"evaluationContainerEntity":{"previewType":"soundClassifier","id":"121ab028-afd1-4511-b847-341c97d45b0e","trainingEvaluationEntity":{"dataSourceID":"D36B56FE-E7ED-4754-91DD-6BC60E42D701","id":"0217c9fd-cb0d-4ba4-9fc4-f2ef91411dc0","evaluationResult":{"soundClassifier":{"confusionMatrix":[{"expected":"background","count":58,"actual":"background"},{"expected":"gunshot","count":42,"actual":"gunshot"}],"statsByLabel":{"gunshot":{"precisionRecall":{"success":{"recall":1,"precision":1}},"count":42},"background":{"count":58,"precisionRecall":{"success":{"precision":1,"recall":1}}}},"accuracy":1}},"dataResult":{"dataAnalysis":{"issues":[{"description":"2 classes found, including background, gunshot","severity":"debug"},{"severity":"warning","description":"Less than 50 total sounds found - add more to improve model validation"},{"severity":"debug","description":"Smallest class is \"gunshot\" with 1 sounds"},{"description":"Largest class is \"background\" with 1 sounds","severity":"debug"}],"summary":{"canUseValidation":0,"classCount":2,"sampleCount":2},"classifierAnalysis":{"labelStats":{"background":1,"gunshot":1}}},"dataSourceID":"D36B56FE-E7ED-4754-91DD-6BC60E42D701","createdDate":"2024-01-27T04:11:49Z","itemsCount":2,"dataURL":"file:\/\/\/Users\/nand\/Downloads\/training\/","classesCount":2},"createdDate":"2024-01-27T04:11:49Z","analysedDataType":"none"},"createdDate":"2024-01-27T04:36:35Z","validationEvaluationEntity":{"evaluationResult":{"soundClassifier":{"accuracy":0,"confusionMatrix":[],"statsByLabel":{}}},"id":"10ae09ea-dbb8-4845-8e91-cd1e3b94fa66","dataResult":{"createdDate":"2024-01-27T04:11:49Z"},"analysedDataType":"auto","createdDate":"2024-01-27T04:11:49Z"},"modifiedDate":"2024-01-27T04:36:35Z","testingEvaluationEntity":{"dataResult":{"createdDate":"2024-01-27T04:11:49Z"},"id":"b1d5e64b-6824-4136-99aa-12c4f91482d4","createdDate":"2024-01-27T04:11:49Z","analysedDataType":"none"},"evaluationEntities":[{"analysedDataType":"none","createdDate":"2024-01-27T04:36:35Z","dataResult":{},"id":"5c9024d6-8923-4e15-a566-2c03b4f63057"}]},"state":"trained","trainingEntity":{"trainingAccuracy":1,"trainingResults":{"soundClassifier":{"statsByLabel":{"gunshot":{"precisionRecall":{"success":{"precision":1,"recall":1}},"count":42},"background":{"count":58,"precisionRecall":{"success":{"precision":1,"recall":1}}}},"accuracy":1,"confusionMatrix":[{"actual":"background","expected":"background","count":58},{"count":42,"actual":"gunshot","expected":"gunshot"}]}},"validationResults":{"soundClassifier":{"confusionMatrix":[],"accuracy":0,"statsByLabel":{}}},"startTime":"2024-01-27T04:36:30Z","finishTime":"2024-01-27T04:36:31Z","snapshottableCheckpoints":{},"progress":[{"tableDone":true,"isLast":false,"tableIndex":1,"percentComplete":0,"currentRowIndex":0,"count":0},{"count":1,"currentRowIndex":0,"isLast":false,"percentComplete":0,"tableDone":false,"tableIndex":0},{"currentRowIndex":0,"tableIndex":2,"scTrainingColumnHeader":{"hasValidation":false,"elapsedTime":0.008523106575012207,"iterationCount":2,"trainingAccuracy":1,"validationAccuracy":0},"isLast":false,"count":2,"percentComplete":0,"tableDone":true}],"checkpointMetrics":{},"featureExtractionCheckpointMayBeAvailable":false,"analysedDataType":"datasource","dataResult":{"itemsCount":2,"dataAnalysis":{"issues":[{"severity":"debug","description":"2 classes found, including background, gunshot"},{"description":"Less than 50 total sounds found - add more to improve model validation","severity":"warning"},{"severity":"debug","description":"Smallest class is \"gunshot\" with 1 sounds"},{"severity":"debug","description":"Largest class is \"background\" with 1 sounds"}],"classifierAnalysis":{"labelStats":{"background":1,"gunshot":1}},"summary":{"classCount":2,"sampleCount":2,"canUseValidation":0}},"createdDate":"2024-01-27T04:11:49Z","classesCount":2,"dataURL":"file:\/\/\/Users\/nand\/Downloads\/training\/","dataSourceID":"D36B56FE-E7ED-4754-91DD-6BC60E42D701"},"validationAccuracy":0,"dataSourceID":"D36B56FE-E7ED-4754-91DD-6BC60E42D701"},"activityEntities":["experimentCreated",[{"id":"E0109DBB-AB5F-4716-81A2-21B0F098DB4E","event":"experimentCreated","createdDate":"2024-01-27T04:11:49Z","title":"Model Source Created","subtitle":"RealertSoundClassifier 1"}],"trainingStarted",[{"createdDate":"2024-01-27T04:36:30Z","event":"trainingStarted","title":"Training Started","id":"3E1747E3-7C71-4125-B37E-63FF9D79265F","subtitle":"25 iterations"}],"trainingDataAdded",[{"createdDate":"2024-01-27T04:36:08Z","id":"FE7285C5-2827-4064-8B9E-06037D5C5A86","event":"trainingDataAdded","title":"Training Data Added","subtitle":"training"}],"trainingFinished",[{"subtitle":"Model converged at 2 iterations","event":"trainingFinished","title":"Training Completed","id":"1061C47B-1D11-4E55-96AA-7AC8FF768D8D","createdDate":"2024-01-27T04:36:31Z"}]],"createdDate":"2024-01-27T04:11:49Z","validationEntity":{"dataResult":{"createdDate":"2024-01-27T04:11:49Z"},"analysedDataType":"auto"},"evaluationEntity":{"analysedDataType":"none","id":"64f5ff95-98bb-4b9d-a71a-f8fe5ea0c74e","dataResult":{}},"preferredFilename":"RealertSoundClassifier 1","version":"1.0","modifiedDate":"2024-01-27T04:36:35Z","title":"RealertSoundClassifier 1","contentDataResult":{"createdDate":"2024-01-27T04:11:49Z"},"snapshotRole":{"withoutSnapshots":0},"modelEntity":{"modifiedDate":"2024-01-27T04:11:49Z","createdDate":"2024-01-27T04:11:49Z","version":"1.0","preferredFilename":"","experimentID":"CF0E1FF1-A31A-4748-8221-AA0D1640B3E9","id":"DFDE7B03-061A-4AF5-AC5C-9EC9F615D0A1","modelURL":"Models\/RealertSoundClassifier%201.mlmodel","title":""},"id":"CF0E1FF1-A31A-4748-8221-AA0D1640B3E9","evaluationState":"uninitialized"}